sync_ics2gcal/__init__.py
sync_ics2gcal/gcal.py
sync_ics2gcal/ical.py
sync_ics2gcal/manage_calendars.py
sync_ics2gcal/py.typed
sync_ics2gcal/sync.py
sync_ics2gcal/sync_calendar.py
sync_ics2gcal-0.1.5.dist-info/LICENSE
sync_ics2gcal-0.1.5.dist-info/METADATA
sync_ics2gcal-0.1.5.dist-info/WHEEL
sync_ics2gcal-0.1.5.dist-info/entry_points.txt
sync_ics2gcal-0.1.5.dist-info/RECORD
