Metadata-Version: 2.1
Name: sync_ics2gcal
Version: 0.1.5
Summary: Sync ics file with Google calendar
Home-page: https://github.com/b4tman/sync_ics2gcal
License: MIT
Keywords: icalendar,sync,google,calendar
Author: Dmitry Belyaev
Author-email: b4tm4n@mail.ru
Requires-Python: >=3.9,<4.0
Classifier: License :: OSI Approved :: MIT License
Classifier: Operating System :: OS Independent
Classifier: Programming Language :: Python :: 3
Classifier: Programming Language :: Python :: 3.9
Classifier: Programming Language :: Python :: 3.10
Classifier: Programming Language :: Python :: 3.11
Classifier: Programming Language :: Python :: 3.12
Requires-Dist: PyYAML (==6.0.2)
Requires-Dist: fire (==0.6.0)
Requires-Dist: google-api-python-client (==2.143.0)
Requires-Dist: google-auth (==2.34.0)
Requires-Dist: icalendar (==5.0.13)
Requires-Dist: pytz (==2024.1)
Project-URL: Repository, https://github.com/b4tman/sync_ics2gcal
